{"version":3,"kind":"Article","sha256":"92cf9b8c16c1cb81c2c0cdc56acb2fd8382b16014383baba12a225da86436459","slug":"blogs","location":"/blogs.md","dependencies":[],"frontmatter":{"title":"Blogs","content_includes_title":false,"authors":[{"id":"tomoyahiroe","url":"https://tomoyahiroe.net","github":"tomoyahiroe"}],"github":"https://github.com/tomoyahiroe/home-page","source_url":"https://github.com/tomoyahiroe/home-page/blob/main/blogs.md","edit_url":"https://github.com/tomoyahiroe/home-page/edit/main/blogs.md","exports":[{"format":"md","filename":"blogs.md","url":"/build/blogs-533963b5e3a76c5fd5f763666fa46a0c.md"}]},"mdast":{"type":"root","children":[{"type":"block","children":[{"type":"card","url":"/blog/2026/web-dev-ynu","children":[{"type":"cardTitle","children":[{"type":"text","value":"Our On-going Project Featured on YNU’s Homepage","key":"SXsVn3TP8I"}],"key":"NcfhvRO5jS"},{"type":"paragraph","children":[{"type":"text","value":"\n\nRecently, [Yokohama National University (YNU) published a feature newsletter](https://www.econ.ynu.ac.jp/education/dsep/soma.html) on the university’s official website highlighting the work my colleagues, my professor, and I have been doing to visualize Japan’s macroeconomic data.\n\n\nOur goal is to make complex economic indicators—such as GDP growth, inflation rates, and labor statistics—accessible and intuitive. Instead of","key":"GC8rB7Xsge"}],"key":"RtcazaUAcI"},{"type":"footer","children":[{"type":"strong","children":[{"type":"text","value":"Date: ","key":"DJHH6rSMnk"}],"key":"rVUW3qcu39"},{"type":"text","value":"January 02, 2026 | ","key":"avo3eUafE6"},{"type":"strong","children":[{"type":"text","value":"Author: ","key":"oedlh3iCQf"}],"key":"STDY2d8mRp"},{"type":"text","value":"tomoyahiroe","key":"A1R2vAU1UM"}],"key":"DUa9EvRP9g"}],"urlSource":"/blog/2026/web-dev-ynu","dataUrl":"/blog.2026.web-dev-ynu.json","internal":true,"protocol":"file","key":"SSEAZVrOOA"}],"key":"OMR2hkpRhv"}],"key":"jRNflSfcpM"},"references":{"cite":{"order":[],"data":{}}},"footer":{"navigation":{"prev":{"title":"Tomoya Hiroe","url":"/","group":"Tomoya Hiroe"},"next":{"title":"Our On-going Project Featured on YNU’s Homepage","url":"/blog/2026/web-dev-ynu","group":"2026"}}},"domain":"http://localhost:3000"}